inquirer/__init__.py
inquirer/errors.py
inquirer/events.py
inquirer/prompt.py
inquirer/questions.py
inquirer/render/__init__.py
inquirer/render/console/__init__.py
inquirer/render/console/_checkbox.py
inquirer/render/console/_confirm.py
inquirer/render/console/_editor.py
inquirer/render/console/_list.py
inquirer/render/console/_other.py
inquirer/render/console/_password.py
inquirer/render/console/_path.py
inquirer/render/console/_text.py
inquirer/render/console/base.py
inquirer/shortcuts.py
inquirer/themes.py
inquirer-3.2.2.dist-info/LICENSE
inquirer-3.2.2.dist-info/METADATA
inquirer-3.2.2.dist-info/WHEEL
inquirer-3.2.2.dist-info/RECORD
